aiccm/__init__.py
aiccm/functions.py
aiccm/__pycache__/__init__.cpython-310.pyc
aiccm/__pycache__/__init__.cpython-311.pyc
aiccm/__pycache__/functions.cpython-310.pyc
aiccm/metrics/__init__.py
aiccm/metrics/concat.py
aiccm/metrics/draw.py
aiccm/metrics/graph.py
aiccm/metrics/instance.py
aiccm/metrics/interface.py
aiccm/metrics/metrics.py
aiccm/metrics/point.py
aiccm/metrics/processor.py
aiccm/metrics/__pycache__/__init__.cpython-310.pyc
aiccm/metrics/__pycache__/concat.cpython-310.pyc
aiccm/metrics/__pycache__/draw.cpython-310.pyc
aiccm/metrics/__pycache__/graph.cpython-310.pyc
aiccm/metrics/__pycache__/instance.cpython-310.pyc
aiccm/metrics/__pycache__/interface.cpython-310.pyc
aiccm/metrics/__pycache__/metrics.cpython-310.pyc
aiccm/metrics/__pycache__/point.cpython-310.pyc
aiccm/metrics/__pycache__/processor.cpython-310.pyc
aiccm/segment/__init__.py
aiccm/segment/detector.py
aiccm/segment/functional.py
aiccm/segment/manager.py
aiccm/segment/nerve.onnx
aiccm/segment/transforms.py
aiccm/segment/__pycache__/__init__.cpython-310.pyc
aiccm/segment/__pycache__/__init__.cpython-311.pyc
aiccm/segment/__pycache__/detector.cpython-310.pyc
aiccm/segment/__pycache__/detector.cpython-311.pyc
aiccm/segment/__pycache__/functional.cpython-310.pyc
aiccm/segment/__pycache__/functional.cpython-311.pyc
aiccm/segment/__pycache__/manager.cpython-310.pyc
aiccm/segment/__pycache__/manager.cpython-311.pyc
aiccm/segment/__pycache__/transforms.cpython-310.pyc
aiccm/segment/__pycache__/transforms.cpython-311.pyc
aiccm/utils/__init__.py
aiccm/utils/io.py
aiccm/utils/morphology.py
aiccm/utils/__pycache__/__init__.cpython-310.pyc
aiccm/utils/__pycache__/__init__.cpython-311.pyc
aiccm/utils/__pycache__/io.cpython-310.pyc
aiccm/utils/__pycache__/morphology.cpython-310.pyc
aiccm-1.1.0.dist-info/licenses/LICENSE.txt
aiccm-1.1.0.dist-info/METADATA
aiccm-1.1.0.dist-info/WHEEL
aiccm-1.1.0.dist-info/top_level.txt
aiccm-1.1.0.dist-info/RECORD
