Metadata-Version: 2.4
Name: aiccm
Version: 1.1.0
Summary: 用于分析和处理角膜共聚焦显微镜角膜神经图像的Python软件包
Home-page: https://https://github.com/SummerColdWind
Author: Qincheng Qiao
Author-email: jugking6688@gmail.com
Classifier: Development Status :: 1 - Planning
Classifier: License :: OSI Approved :: GNU General Public License v3 (GPLv3)
Classifier: Topic :: Scientific/Engineering :: Medical Science Apps.
Requires-Python: >=3.9
License-File: LICENSE.txt
Requires-Dist: opencv-python
Requires-Dist: numpy
Requires-Dist: onnxruntime
Requires-Dist: pillow
Requires-Dist: scipy
Requires-Dist: scikit-image
Requires-Dist: onnx
Dynamic: author
Dynamic: author-email
Dynamic: classifier
Dynamic: description
Dynamic: description-content-type
Dynamic: home-page
Dynamic: license-file
Dynamic: requires-dist
Dynamic: requires-python
Dynamic: summary
